algocash_sdk/__init__.py
algocash_sdk/api_client.py
algocash_sdk/callback.py
algocash_sdk/configuration.py
algocash_sdk/rest.py
algocash_sdk/api/__init__.py
algocash_sdk/api/deposit_api.py
algocash_sdk/api/payout_api.py
algocash_sdk/models/__init__.py
algocash_sdk/models/address.py
algocash_sdk/models/bank.py
algocash_sdk/models/callback_payload.py
algocash_sdk/models/deposit_request.py
algocash_sdk/models/deposit_status_info.py
algocash_sdk/models/deposit_status_response.py
algocash_sdk/models/deposit_success.py
algocash_sdk/models/error.py
algocash_sdk/models/payer.py
algocash_sdk/models/payout_request.py
algocash_sdk/models/payout_status_info.py
algocash_sdk/models/payout_status_response.py
algocash_sdk/models/payout_success.py
algocash_sdk/models/url.py
test/__init__.py
test/test_callback.py
test/test_deposit_api.py
test/test_deposit_status_api.py
test/test_payout_api.py
test/test_payout_status_api.py
algocash_sdk-1.3.0.dist-info/METADATA
algocash_sdk-1.3.0.dist-info/WHEEL
algocash_sdk-1.3.0.dist-info/top_level.txt
algocash_sdk-1.3.0.dist-info/RECORD
