Metadata-Version: 2.1
Name: algocash-sdk
Version: 1.3.0
Summary: Algocash API
Home-page: 
Author-email: loganph.work@gmail.com
Keywords: Python,Algocash API
Requires-Dist: urllib3 (>=1.15)
Requires-Dist: six (>=1.10)
Requires-Dist: certifi
Requires-Dist: python-dateutil
